unicode_syllable/__init__.py
unicode_syllable/unicode.py
unicode_syllable-0.1.0.dist-info/LICENSE
unicode_syllable-0.1.0.dist-info/METADATA
unicode_syllable-0.1.0.dist-info/WHEEL
unicode_syllable-0.1.0.dist-info/top_level.txt
unicode_syllable-0.1.0.dist-info/RECORD
